README
setup.cfg
setup.py
launch_control_tool/__init__.py
launch_control_tool/commands.py
launch_control_tool/main.py
launch_control_tool.egg-info/PKG-INFO
launch_control_tool.egg-info/SOURCES.txt
launch_control_tool.egg-info/dependency_links.txt
launch_control_tool.egg-info/entry_points.txt
launch_control_tool.egg-info/requires.txt
launch_control_tool.egg-info/top_level.txt
launch_control_tool.egg-info/zip-safe
launch_control_tool/tests/__init__.py
launch_control_tool/tests/test_commands.py