Metadata-Version: 1.0
Name: launch-control-tool
Version: 0.5.2
Summary: Command line utility for Launch Control
Home-page: https://launchpad.net/launch-control-tool
Author: Zygmunt Krynicki
Author-email: zygmunt.krynicki@linaro.org
License: LGPLv3
Platform: UNKNOWN
Classifier: Development Status :: 4 - Beta
Classifier: Intended Audience :: Developers
Classifier: License :: OSI Approved :: GNU Library or Lesser General Public License (LGPL)
Classifier: Operating System :: OS Independent
Classifier: Programming Language :: Python :: 2.6
Classifier: Programming Language :: Python :: 2.7
Classifier: Topic :: Software Development :: Testing
